{
  "available": true,
  "labels": [
    "Critical",
    "High",
    "Medium",
    "Low",
    "No-score"
  ],
  "nvd": {
    "data": [
      303,
      220,
      70,
      1,
      12
    ],
    "total": 606
  },
  "euvd": {
    "data": [
      303,
      220,
      70,
      1,
      11
    ],
    "total": 605
  },
  "cnvd": {
    "data": [
      132,
      111,
      25,
      0,
      0
    ],
    "total": 268
  },
  "jvn": {
    "data": [
      140,
      130,
      35,
      0,
      1
    ],
    "total": 306
  },
  "bdu": {
    "data": [
      280,
      197,
      47,
      1,
      1
    ],
    "total": 526
  }
}