{
  "available": true,
  "categories": [
    {
      "title": "Attack Vector",
      "key": "av"
    },
    {
      "title": "Attack Complexity",
      "key": "ac"
    },
    {
      "title": "Privileges Required",
      "key": "pr"
    },
    {
      "title": "User Interaction",
      "key": "ui"
    },
    {
      "title": "Scope",
      "key": "scope"
    },
    {
      "title": "Confidentiality Impact",
      "key": "confidentiality"
    },
    {
      "title": "Integrity Impact",
      "key": "integrity"
    },
    {
      "title": "Availability Impact",
      "key": "availability"
    }
  ],
  "av": {
    "labels": [
      "Network",
      "Adjacent",
      "Local",
      "Physical"
    ],
    "data": [
      3534,
      93,
      601,
      11
    ]
  },
  "ac": {
    "labels": [
      "Low",
      "High"
    ],
    "data": [
      3931,
      308
    ]
  },
  "pr": {
    "labels": [
      "None",
      "Low",
      "High"
    ],
    "data": [
      3131,
      923,
      185
    ]
  },
  "ui": {
    "labels": [
      "None",
      "Required"
    ],
    "data": [
      3388,
      851
    ]
  },
  "scope": {
    "labels": [
      "Unchanged",
      "Changed"
    ],
    "data": [
      3568,
      671
    ]
  },
  "confidentiality": {
    "labels": [
      "None",
      "Low",
      "High"
    ],
    "data": [
      324,
      558,
      3357
    ]
  },
  "integrity": {
    "labels": [
      "None",
      "Low",
      "High"
    ],
    "data": [
      740,
      553,
      2946
    ]
  },
  "availability": {
    "labels": [
      "None",
      "Low",
      "High"
    ],
    "data": [
      1052,
      278,
      2909
    ]
  }
}