{
  "available": true,
  "kevTotal": 4896,
  "otherTotal": 1592,
  "both": 1592,
  "kevOnly": 3304,
  "otherOnly": 0,
  "stats": [
    {
      "number": "4,896",
      "desc": "KEVs (combined catalog)"
    },
    {
      "number": "1,592",
      "desc": "In both KEVs and CISA KEV"
    },
    {
      "number": "1,592",
      "desc": "CISA KEV catalog"
    }
  ],
  "cisaTotal": 1592,
  "cisaOnly": 0,
  "labels": [
    "KEVs only",
    "Both",
    "CISA KEV only"
  ],
  "data": [
    3304,
    1592,
    0
  ]
}