{
  "available": true,
  "labels": [
    "Critical",
    "High",
    "Medium",
    "Low",
    "No-score"
  ],
  "nvd": {
    "data": [
      1750,
      2016,
      899,
      32,
      121
    ],
    "total": 4818
  },
  "euvd": {
    "data": [
      1750,
      2016,
      899,
      32,
      114
    ],
    "total": 4811
  },
  "cnvd": {
    "data": [
      631,
      763,
      272,
      3,
      3
    ],
    "total": 1672
  },
  "jvn": {
    "data": [
      1611,
      1891,
      816,
      24,
      3
    ],
    "total": 4345
  }
}