{
  "available": true,
  "labels": [
    "Critical",
    "High",
    "Medium",
    "Low",
    "No-score"
  ],
  "nvd": {
    "data": [
      1848,
      2120,
      934,
      35,
      118
    ],
    "total": 5055
  },
  "euvd": {
    "data": [
      1848,
      2120,
      934,
      35,
      115
    ],
    "total": 5052
  },
  "cnvd": {
    "data": [
      224,
      395,
      112,
      2,
      1
    ],
    "total": 734
  },
  "jvn": {
    "data": [
      1598,
      1891,
      778,
      23,
      4
    ],
    "total": 4294
  },
  "bdu": {
    "data": [
      937,
      1237,
      357,
      13,
      29
    ],
    "total": 2573
  }
}