{
  "available": true,
  "kevTotal": 4955,
  "otherTotal": 4952,
  "both": 4952,
  "kevOnly": 3,
  "otherOnly": 0,
  "stats": [
    {
      "number": "4,955",
      "desc": "KEVs (combined catalog)"
    },
    {
      "number": "4,952",
      "desc": "In both KEVs and VulnCheck KEV"
    },
    {
      "number": "4,952",
      "desc": "VulnCheck KEV catalog"
    }
  ],
  "vulncheckTotal": 4952,
  "vulncheckOnly": 0,
  "labels": [
    "KEVs only",
    "Both",
    "VulnCheck only"
  ],
  "data": [
    3,
    4952,
    0
  ]
}